SFC_Torch/Fmodel.py
SFC_Torch/VERSION
SFC_Torch/__init__.py
SFC_Torch/io.py
SFC_Torch/mask.py
SFC_Torch/packingscore.py
SFC_Torch/patterson.py
SFC_Torch/symmetry.py
SFC_Torch/utils.py
SFC_Torch/voxel.py
tests/__init__.py
tests/conftest.py
tests/test_Fmodel.py
tests/test_io.py
tests/test_patterson.py
tests/test_voxel.py
sfcalculator_torch-0.2.5.dist-info/METADATA
sfcalculator_torch-0.2.5.dist-info/WHEEL
sfcalculator_torch-0.2.5.dist-info/top_level.txt
sfcalculator_torch-0.2.5.dist-info/RECORD
