Metadata-Version: 2.4
Name: sfcalculator_torch
Version: 0.2.5
Summary: A differentiable pipeline connecting molecule models and crystallpgraphy data
Home-page: https://github.com/Hekstra-Lab/SFcalculator
Author: Minhaun Li
Author-email: minhuanli@g.harvard.edu
License: MIT
Requires-Python: >=3.9
Requires-Dist: gemmi<=0.6.7,>=0.5.6
Requires-Dist: reciprocalspaceship<=1.0.3,>=0.9.18
Requires-Dist: numpy<2.0.0
Requires-Dist: tqdm
Requires-Dist: loguru
Provides-Extra: test
Requires-Dist: pytest; extra == "test"
Requires-Dist: pytest-cov; extra == "test"
Dynamic: author
Dynamic: author-email
Dynamic: home-page
Dynamic: license
Dynamic: provides-extra
Dynamic: requires-dist
Dynamic: requires-python
Dynamic: summary
